prevent_cli/__init__.py
prevent_cli/fallbacks.py
prevent_cli/main.py
prevent_cli/options.py
prevent_cli/commands/__init__.py
prevent_cli/commands/upload.py
sentry_prevent_cli-11.2.6.dist-info/licenses/LICENSE
sentry_prevent_cli-11.2.6.dist-info/METADATA
sentry_prevent_cli-11.2.6.dist-info/WHEEL
sentry_prevent_cli-11.2.6.dist-info/entry_points.txt
sentry_prevent_cli-11.2.6.dist-info/top_level.txt
sentry_prevent_cli-11.2.6.dist-info/RECORD
