Metadata-Version: 2.4
Name: sentry-prevent-cli
Version: 11.2.6
Summary: Sentry Prevent Command Line Interface
Author-email: Sentry <oss@sentry.io>
Requires-Python: >=3.9
License-File: LICENSE
Requires-Dist: codecov-cli==11.2.6
Requires-Dist: click<8.3.0,>=8.0.0
Requires-Dist: sentry-sdk==2.*
Dynamic: license-file
